ccdgen/__init__.py
ccdgen/__main__.py
ccdgen-0.0.11.dist-info/LICENSE
ccdgen-0.0.11.dist-info/METADATA
ccdgen-0.0.11.dist-info/WHEEL
ccdgen-0.0.11.dist-info/top_level.txt
ccdgen-0.0.11.dist-info/RECORD
