Metadata-Version: 2.1
Name: ccdgen
Version: 0.0.11
Summary: Generates compilation databases by capturing standard output from Make
Author: Tim Brewis
Author-email: timbrewis27@gmail.com
License: Apache-2.0
Project-URL: Source, https://github.com/t-bre/ccdgen
Project-URL: Tracker, https://github.com/t-bre/ccdgen
Keywords: make
Classifier: Development Status :: 4 - Beta
Classifier: Environment :: Console
Classifier: Intended Audience :: Developers
Classifier: Topic :: Software Development :: Build Tools
Classifier: License :: OSI Approved :: Apache Software License
Classifier: Programming Language :: Python :: 3.10
License-File: LICENSE
